[
    {
        "ending": 1527829200.0,
        "entries": 874,
        "exits": 859
    },
    {
        "ending": 1527843600.0,
        "entries": 96,
        "exits": 140
    },
    {
        "ending": 1527858000.0,
        "entries": 3126,
        "exits": 4522
    },
    {
        "ending": 1527872400.0,
        "entries": 2444,
        "exits": 5677
    },
    {
        "ending": 1527886800.0,
        "entries": 5641,
        "exits": 3560
    },
    {
        "ending": 1527901200.0,
        "entries": 6425,
        "exits": 3199
    },
    {
        "ending": 1527915600.0,
        "entries": 1190,
        "exits": 1130
    },
    {
        "ending": 1527930000.0,
        "entries": 140,
        "exits": 286
    },
    {
        "ending": 1527944400.0,
        "entries": 727,
        "exits": 820
    },
    {
        "ending": 1527958800.0,
        "entries": 1648,
        "exits": 2585
    },
    {
        "ending": 1527973200.0,
        "entries": 3069,
        "exits": 2652
    },
    {
        "ending": 1527987600.0,
        "entries": 2609,
        "exits": 1714
    },
    {
        "ending": 1528002000.0,
        "entries": 927,
        "exits": 1001
    },
    {
        "ending": 1528016400.0,
        "entries": 103,
        "exits": 237
    },
    {
        "ending": 1528030800.0,
        "entries": 515,
        "exits": 570
    },
    {
        "ending": 1528045200.0,
        "entries": 1454,
        "exits": 1756
    },
    {
        "ending": 1528059600.0,
        "entries": 2254,
        "exits": 1821
    },
    {
        "ending": 1528074000.0,
        "entries": 1954,
        "exits": 1524
    },
    {
        "ending": 1528088400.0,
        "entries": 535,
        "exits": 681
    },
    {
        "ending": 1528102800.0,
        "entries": 126,
        "exits": 133
    },
    {
        "ending": 1528117200.0,
        "entries": 3132,
        "exits": 5819
    },
    {
        "ending": 1528131600.0,
        "entries": 2757,
        "exits": 5162
    },
    {
        "ending": 1528146000.0,
        "entries": 4719,
        "exits": 3279
    },
    {
        "ending": 1528160400.0,
        "entries": 7713,
        "exits": 3293
    },
    {
        "ending": 1528174800.0,
        "entries": 881,
        "exits": 829
    },
    {
        "ending": 1528189200.0,
        "entries": 147,
        "exits": 203
    },
    {
        "ending": 1528203600.0,
        "entries": 3168,
        "exits": 5524
    },
    {
        "ending": 1528218000.0,
        "entries": 3030,
        "exits": 5529
    },
    {
        "ending": 1528232400.0,
        "entries": 5016,
        "exits": 3266
    },
    {
        "ending": 1528246800.0,
        "entries": 7889,
        "exits": 3232
    },
    {
        "ending": 1528261200.0,
        "entries": 948,
        "exits": 935
    },
    {
        "ending": 1528275600.0,
        "entries": 128,
        "exits": 168
    },
    {
        "ending": 1528290000.0,
        "entries": 3203,
        "exits": 5484
    },
    {
        "ending": 1528304400.0,
        "entries": 2833,
        "exits": 5796
    },
    {
        "ending": 1528318800.0,
        "entries": 5161,
        "exits": 3134
    },
    {
        "ending": 1528333200.0,
        "entries": 8091,
        "exits": 3344
    },
    {
        "ending": 1528347600.0,
        "entries": 936,
        "exits": 978
    },
    {
        "ending": 1528362000.0,
        "entries": 151,
        "exits": 134
    },
    {
        "ending": 1528376400.0,
        "entries": 2939,
        "exits": 5386
    },
    {
        "ending": 1528390800.0,
        "entries": 2917,
        "exits": 5864
    },
    {
        "ending": 1528405200.0,
        "entries": 5289,
        "exits": 3625
    },
    {
        "ending": 1528419600.0,
        "entries": 8044,
        "exits": 3345
    },
    {
        "ending": 1528434000.0,
        "entries": 1113,
        "exits": 1051
    },
    {
        "ending": 1528448400.0,
        "entries": 162,
        "exits": 157
    },
    {
        "ending": 1528462800.0,
        "entries": 2792,
        "exits": 4907
    },
    {
        "ending": 1528477200.0,
        "entries": 2942,
        "exits": 5838
    },
    {
        "ending": 1528491600.0,
        "entries": 6134,
        "exits": 3655
    },
    {
        "ending": 1528506000.0,
        "entries": 6551,
        "exits": 3470
    },
    {
        "ending": 1528520400.0,
        "entries": 1484,
        "exits": 1154
    },
    {
        "ending": 1528534800.0,
        "entries": 168,
        "exits": 309
    },
    {
        "ending": 1528549200.0,
        "entries": 674,
        "exits": 770
    },
    {
        "ending": 1528563600.0,
        "entries": 1710,
        "exits": 2191
    },
    {
        "ending": 1528578000.0,
        "entries": 3525,
        "exits": 2406
    },
    {
        "ending": 1528592400.0,
        "entries": 2731,
        "exits": 1855
    },
    {
        "ending": 1528606800.0,
        "entries": 1058,
        "exits": 1115
    },
    {
        "ending": 1528621200.0,
        "entries": 134,
        "exits": 287
    },
    {
        "ending": 1528635600.0,
        "entries": 452,
        "exits": 575
    },
    {
        "ending": 1528650000.0,
        "entries": 1528,
        "exits": 1606
    },
    {
        "ending": 1528664400.0,
        "entries": 2518,
        "exits": 1592
    },
    {
        "ending": 1528678800.0,
        "entries": 1619,
        "exits": 1337
    },
    {
        "ending": 1528693200.0,
        "entries": 488,
        "exits": 613
    },
    {
        "ending": 1528707600.0,
        "entries": 112,
        "exits": 147
    },
    {
        "ending": 1528722000.0,
        "entries": 3112,
        "exits": 5375
    },
    {
        "ending": 1528736400.0,
        "entries": 2772,
        "exits": 5531
    },
    {
        "ending": 1528750800.0,
        "entries": 5040,
        "exits": 3422
    },
    {
        "ending": 1528765200.0,
        "entries": 8104,
        "exits": 3340
    },
    {
        "ending": 1528779600.0,
        "entries": 1029,
        "exits": 889
    },
    {
        "ending": 1528794000.0,
        "entries": 137,
        "exits": 168
    },
    {
        "ending": 1528808400.0,
        "entries": 3268,
        "exits": 5438
    },
    {
        "ending": 1528822800.0,
        "entries": 2738,
        "exits": 5823
    },
    {
        "ending": 1528837200.0,
        "entries": 5241,
        "exits": 3657
    },
    {
        "ending": 1528851600.0,
        "entries": 8410,
        "exits": 3461
    },
    {
        "ending": 1528866000.0,
        "entries": 962,
        "exits": 1017
    },
    {
        "ending": 1528880400.0,
        "entries": 159,
        "exits": 156
    },
    {
        "ending": 1528894800.0,
        "entries": 3250,
        "exits": 5150
    },
    {
        "ending": 1528909200.0,
        "entries": 2657,
        "exits": 4621
    },
    {
        "ending": 1528923600.0,
        "entries": 4916,
        "exits": 3363
    },
    {
        "ending": 1528938000.0,
        "entries": 7634,
        "exits": 3169
    },
    {
        "ending": 1528952400.0,
        "entries": 959,
        "exits": 900
    },
    {
        "ending": 1528966800.0,
        "entries": 144,
        "exits": 167
    },
    {
        "ending": 1528981200.0,
        "entries": 3114,
        "exits": 5471
    },
    {
        "ending": 1528995600.0,
        "entries": 3025,
        "exits": 6179
    },
    {
        "ending": 1529010000.0,
        "entries": 5659,
        "exits": 3626
    },
    {
        "ending": 1529024400.0,
        "entries": 8106,
        "exits": 3533
    },
    {
        "ending": 1529038800.0,
        "entries": 1275,
        "exits": 1230
    },
    {
        "ending": 1529053200.0,
        "entries": 175,
        "exits": 205
    },
    {
        "ending": 1529067600.0,
        "entries": 2699,
        "exits": 4563
    },
    {
        "ending": 1529082000.0,
        "entries": 2851,
        "exits": 5654
    },
    {
        "ending": 1529096400.0,
        "entries": 6142,
        "exits": 3712
    },
    {
        "ending": 1529110800.0,
        "entries": 6508,
        "exits": 3411
    },
    {
        "ending": 1529125200.0,
        "entries": 1629,
        "exits": 1302
    },
    {
        "ending": 1529139600.0,
        "entries": 162,
        "exits": 314
    },
    {
        "ending": 1529154000.0,
        "entries": 729,
        "exits": 866
    },
    {
        "ending": 1529168400.0,
        "entries": 1703,
        "exits": 2850
    },
    {
        "ending": 1529182800.0,
        "entries": 3230,
        "exits": 2699
    },
    {
        "ending": 1529197200.0,
        "entries": 3590,
        "exits": 2269
    },
    {
        "ending": 1529211600.0,
        "entries": 1028,
        "exits": 1153
    },
    {
        "ending": 1529226000.0,
        "entries": 137,
        "exits": 279
    },
    {
        "ending": 1529240400.0,
        "entries": 442,
        "exits": 498
    },
    {
        "ending": 1529254800.0,
        "entries": 1388,
        "exits": 2394
    },
    {
        "ending": 1529269200.0,
        "entries": 2949,
        "exits": 2258
    },
    {
        "ending": 1529283600.0,
        "entries": 2877,
        "exits": 1617
    },
    {
        "ending": 1529298000.0,
        "entries": 770,
        "exits": 760
    },
    {
        "ending": 1529312400.0,
        "entries": 80,
        "exits": 172
    },
    {
        "ending": 1529326800.0,
        "entries": 3008,
        "exits": 5252
    },
    {
        "ending": 1529341200.0,
        "entries": 2701,
        "exits": 5705
    },
    {
        "ending": 1529355600.0,
        "entries": 5114,
        "exits": 3434
    },
    {
        "ending": 1529370000.0,
        "entries": 7774,
        "exits": 3160
    },
    {
        "ending": 1529384400.0,
        "entries": 901,
        "exits": 865
    },
    {
        "ending": 1529398800.0,
        "entries": 143,
        "exits": 195
    },
    {
        "ending": 1529413200.0,
        "entries": 2995,
        "exits": 4993
    },
    {
        "ending": 1529427600.0,
        "entries": 2938,
        "exits": 6224
    },
    {
        "ending": 1529442000.0,
        "entries": 5093,
        "exits": 3266
    },
    {
        "ending": 1529456400.0,
        "entries": 7939,
        "exits": 3281
    },
    {
        "ending": 1529470800.0,
        "entries": 1146,
        "exits": 1122
    },
    {
        "ending": 1529485200.0,
        "entries": 103,
        "exits": 91
    },
    {
        "ending": 1529499600.0,
        "entries": 2990,
        "exits": 5406
    },
    {
        "ending": 1529514000.0,
        "entries": 2945,
        "exits": 5516
    },
    {
        "ending": 1529528400.0,
        "entries": 5216,
        "exits": 3313
    },
    {
        "ending": 1529542800.0,
        "entries": 8075,
        "exits": 3533
    },
    {
        "ending": 1529557200.0,
        "entries": 885,
        "exits": 1011
    },
    {
        "ending": 1529571600.0,
        "entries": 82,
        "exits": 123
    },
    {
        "ending": 1529586000.0,
        "entries": 3060,
        "exits": 5053
    },
    {
        "ending": 1529600400.0,
        "entries": 2895,
        "exits": 5756
    },
    {
        "ending": 1529614800.0,
        "entries": 5333,
        "exits": 3581
    },
    {
        "ending": 1529629200.0,
        "entries": 7984,
        "exits": 3543
    },
    {
        "ending": 1529643600.0,
        "entries": 1042,
        "exits": 1102
    },
    {
        "ending": 1529658000.0,
        "entries": 113,
        "exits": 117
    },
    {
        "ending": 1529672400.0,
        "entries": 2788,
        "exits": 4544
    },
    {
        "ending": 1529686800.0,
        "entries": 2691,
        "exits": 5348
    },
    {
        "ending": 1529701200.0,
        "entries": 6145,
        "exits": 3778
    },
    {
        "ending": 1529715600.0,
        "entries": 6688,
        "exits": 3476
    },
    {
        "ending": 1529730000.0,
        "entries": 1306,
        "exits": 1143
    },
    {
        "ending": 1529744400.0,
        "entries": 170,
        "exits": 263
    },
    {
        "ending": 1529758800.0,
        "entries": 645,
        "exits": 667
    },
    {
        "ending": 1529773200.0,
        "entries": 1372,
        "exits": 1930
    },
    {
        "ending": 1529787600.0,
        "entries": 2317,
        "exits": 2054
    },
    {
        "ending": 1529802000.0,
        "entries": 2293,
        "exits": 1547
    },
    {
        "ending": 1529816400.0,
        "entries": 862,
        "exits": 980
    },
    {
        "ending": 1529830800.0,
        "entries": 143,
        "exits": 271
    },
    {
        "ending": 1529845200.0,
        "entries": 453,
        "exits": 611
    },
    {
        "ending": 1529859600.0,
        "entries": 1737,
        "exits": 2365
    },
    {
        "ending": 1529874000.0,
        "entries": 2944,
        "exits": 2496
    },
    {
        "ending": 1529888400.0,
        "entries": 2806,
        "exits": 2101
    },
    {
        "ending": 1529902800.0,
        "entries": 786,
        "exits": 817
    },
    {
        "ending": 1529917200.0,
        "entries": 98,
        "exits": 188
    },
    {
        "ending": 1529931600.0,
        "entries": 3130,
        "exits": 4746
    },
    {
        "ending": 1529946000.0,
        "entries": 2853,
        "exits": 6337
    },
    {
        "ending": 1529960400.0,
        "entries": 5325,
        "exits": 3578
    },
    {
        "ending": 1529974800.0,
        "entries": 8299,
        "exits": 3305
    },
    {
        "ending": 1529989200.0,
        "entries": 1042,
        "exits": 943
    },
    {
        "ending": 1530003600.0,
        "entries": 137,
        "exits": 195
    },
    {
        "ending": 1530018000.0,
        "entries": 3103,
        "exits": 4873
    },
    {
        "ending": 1530032400.0,
        "entries": 2973,
        "exits": 6376
    },
    {
        "ending": 1530046800.0,
        "entries": 5420,
        "exits": 3398
    },
    {
        "ending": 1530061200.0,
        "entries": 8576,
        "exits": 3489
    },
    {
        "ending": 1530075600.0,
        "entries": 1170,
        "exits": 1055
    },
    {
        "ending": 1530090000.0,
        "entries": 163,
        "exits": 218
    },
    {
        "ending": 1530104400.0,
        "entries": 3051,
        "exits": 5169
    },
    {
        "ending": 1530118800.0,
        "entries": 2925,
        "exits": 5720
    },
    {
        "ending": 1530133200.0,
        "entries": 5506,
        "exits": 3470
    },
    {
        "ending": 1530147600.0,
        "entries": 8391,
        "exits": 3258
    },
    {
        "ending": 1530162000.0,
        "entries": 918,
        "exits": 1100
    },
    {
        "ending": 1530176400.0,
        "entries": 125,
        "exits": 178
    },
    {
        "ending": 1530190800.0,
        "entries": 3208,
        "exits": 5040
    },
    {
        "ending": 1530205200.0,
        "entries": 2570,
        "exits": 5298
    },
    {
        "ending": 1530219600.0,
        "entries": 5003,
        "exits": 3522
    },
    {
        "ending": 1530234000.0,
        "entries": 8700,
        "exits": 3622
    },
    {
        "ending": 1530248400.0,
        "entries": 1124,
        "exits": 1242
    },
    {
        "ending": 1530262800.0,
        "entries": 119,
        "exits": 197
    },
    {
        "ending": 1530277200.0,
        "entries": 2868,
        "exits": 4810
    },
    {
        "ending": 1530291600.0,
        "entries": 3102,
        "exits": 6011
    },
    {
        "ending": 1530306000.0,
        "entries": 7102,
        "exits": 3809
    },
    {
        "ending": 1530320400.0,
        "entries": 6910,
        "exits": 3428
    },
    {
        "ending": 1530334800.0,
        "entries": 1956,
        "exits": 1749
    },
    {
        "ending": 1530349200.0,
        "entries": 242,
        "exits": 307
    },
    {
        "ending": 1530363600.0,
        "entries": 1055,
        "exits": 1148
    },
    {
        "ending": 1530378000.0,
        "entries": 2678,
        "exits": 4262
    },
    {
        "ending": 1530392400.0,
        "entries": 4604,
        "exits": 4075
    },
    {
        "ending": 1530406800.0,
        "entries": 4830,
        "exits": 2729
    }
]