[
    {
        "ending": 1525150800.0,
        "entries": 40,
        "exits": 43
    },
    {
        "ending": 1525165200.0,
        "entries": 27,
        "exits": 7
    },
    {
        "ending": 1525179600.0,
        "entries": 1741,
        "exits": 86
    },
    {
        "ending": 1525194000.0,
        "entries": 765,
        "exits": 134
    },
    {
        "ending": 1525208400.0,
        "entries": 401,
        "exits": 138
    },
    {
        "ending": 1525222800.0,
        "entries": 231,
        "exits": 151
    },
    {
        "ending": 1525237200.0,
        "entries": 48,
        "exits": 45
    },
    {
        "ending": 1525251600.0,
        "entries": 35,
        "exits": 8
    },
    {
        "ending": 1525266000.0,
        "entries": 1727,
        "exits": 73
    },
    {
        "ending": 1525280400.0,
        "entries": 751,
        "exits": 102
    },
    {
        "ending": 1525294800.0,
        "entries": 424,
        "exits": 177
    },
    {
        "ending": 1525309200.0,
        "entries": 223,
        "exits": 149
    },
    {
        "ending": 1525323600.0,
        "entries": 60,
        "exits": 41
    },
    {
        "ending": 1525338000.0,
        "entries": 32,
        "exits": 9
    },
    {
        "ending": 1525352400.0,
        "entries": 1755,
        "exits": 54
    },
    {
        "ending": 1525366800.0,
        "entries": 798,
        "exits": 91
    },
    {
        "ending": 1525381200.0,
        "entries": 404,
        "exits": 133
    },
    {
        "ending": 1525395600.0,
        "entries": 254,
        "exits": 134
    },
    {
        "ending": 1525410000.0,
        "entries": 54,
        "exits": 56
    },
    {
        "ending": 1525424400.0,
        "entries": 33,
        "exits": 10
    },
    {
        "ending": 1525438800.0,
        "entries": 1648,
        "exits": 74
    },
    {
        "ending": 1525453200.0,
        "entries": 712,
        "exits": 85
    },
    {
        "ending": 1525467600.0,
        "entries": 417,
        "exits": 130
    },
    {
        "ending": 1525482000.0,
        "entries": 236,
        "exits": 181
    },
    {
        "ending": 1525496400.0,
        "entries": 57,
        "exits": 53
    },
    {
        "ending": 1525510800.0,
        "entries": 22,
        "exits": 11
    },
    {
        "ending": 1525525200.0,
        "entries": 542,
        "exits": 55
    },
    {
        "ending": 1525539600.0,
        "entries": 637,
        "exits": 119
    },
    {
        "ending": 1525554000.0,
        "entries": 364,
        "exits": 119
    },
    {
        "ending": 1525568400.0,
        "entries": 194,
        "exits": 106
    },
    {
        "ending": 1525582800.0,
        "entries": 45,
        "exits": 53
    },
    {
        "ending": 1525597200.0,
        "entries": 12,
        "exits": 6
    },
    {
        "ending": 1525611600.0,
        "entries": 294,
        "exits": 38
    },
    {
        "ending": 1525626000.0,
        "entries": 520,
        "exits": 92
    },
    {
        "ending": 1525640400.0,
        "entries": 283,
        "exits": 62
    },
    {
        "ending": 1525654800.0,
        "entries": 126,
        "exits": 85
    },
    {
        "ending": 1525669200.0,
        "entries": 28,
        "exits": 36
    },
    {
        "ending": 1525683600.0,
        "entries": 34,
        "exits": 8
    },
    {
        "ending": 1525698000.0,
        "entries": 1666,
        "exits": 54
    },
    {
        "ending": 1525712400.0,
        "entries": 790,
        "exits": 85
    },
    {
        "ending": 1525726800.0,
        "entries": 396,
        "exits": 137
    },
    {
        "ending": 1525741200.0,
        "entries": 207,
        "exits": 152
    },
    {
        "ending": 1525755600.0,
        "entries": 67,
        "exits": 37
    },
    {
        "ending": 1525770000.0,
        "entries": 36,
        "exits": 7
    },
    {
        "ending": 1525784400.0,
        "entries": 1752,
        "exits": 64
    },
    {
        "ending": 1525798800.0,
        "entries": 808,
        "exits": 91
    },
    {
        "ending": 1525813200.0,
        "entries": 428,
        "exits": 134
    },
    {
        "ending": 1525827600.0,
        "entries": 248,
        "exits": 145
    },
    {
        "ending": 1525842000.0,
        "entries": 52,
        "exits": 38
    },
    {
        "ending": 1525856400.0,
        "entries": 37,
        "exits": 6
    },
    {
        "ending": 1525870800.0,
        "entries": 1751,
        "exits": 69
    },
    {
        "ending": 1525885200.0,
        "entries": 799,
        "exits": 102
    },
    {
        "ending": 1525899600.0,
        "entries": 428,
        "exits": 153
    },
    {
        "ending": 1525914000.0,
        "entries": 220,
        "exits": 120
    },
    {
        "ending": 1525928400.0,
        "entries": 42,
        "exits": 43
    },
    {
        "ending": 1525942800.0,
        "entries": 35,
        "exits": 8
    },
    {
        "ending": 1525957200.0,
        "entries": 1730,
        "exits": 62
    },
    {
        "ending": 1525971600.0,
        "entries": 748,
        "exits": 84
    },
    {
        "ending": 1525986000.0,
        "entries": 413,
        "exits": 144
    },
    {
        "ending": 1526000400.0,
        "entries": 248,
        "exits": 148
    },
    {
        "ending": 1526014800.0,
        "entries": 43,
        "exits": 37
    },
    {
        "ending": 1526029200.0,
        "entries": 28,
        "exits": 5
    },
    {
        "ending": 1526043600.0,
        "entries": 1614,
        "exits": 77
    },
    {
        "ending": 1526058000.0,
        "entries": 751,
        "exits": 89
    },
    {
        "ending": 1526072400.0,
        "entries": 401,
        "exits": 138
    },
    {
        "ending": 1526086800.0,
        "entries": 235,
        "exits": 141
    },
    {
        "ending": 1526101200.0,
        "entries": 65,
        "exits": 47
    },
    {
        "ending": 1526115600.0,
        "entries": 20,
        "exits": 13
    },
    {
        "ending": 1526130000.0,
        "entries": 495,
        "exits": 61
    },
    {
        "ending": 1526144400.0,
        "entries": 572,
        "exits": 91
    },
    {
        "ending": 1526158800.0,
        "entries": 305,
        "exits": 91
    },
    {
        "ending": 1526173200.0,
        "entries": 151,
        "exits": 124
    },
    {
        "ending": 1526187600.0,
        "entries": 35,
        "exits": 51
    },
    {
        "ending": 1526202000.0,
        "entries": 12,
        "exits": 7
    },
    {
        "ending": 1526216400.0,
        "entries": 303,
        "exits": 36
    },
    {
        "ending": 1526230800.0,
        "entries": 542,
        "exits": 96
    },
    {
        "ending": 1526245200.0,
        "entries": 250,
        "exits": 76
    },
    {
        "ending": 1526259600.0,
        "entries": 103,
        "exits": 105
    },
    {
        "ending": 1526274000.0,
        "entries": 29,
        "exits": 38
    },
    {
        "ending": 1526288400.0,
        "entries": 35,
        "exits": 5
    },
    {
        "ending": 1526302800.0,
        "entries": 1673,
        "exits": 64
    },
    {
        "ending": 1526317200.0,
        "entries": 760,
        "exits": 84
    },
    {
        "ending": 1526331600.0,
        "entries": 424,
        "exits": 131
    },
    {
        "ending": 1526346000.0,
        "entries": 222,
        "exits": 134
    },
    {
        "ending": 1526360400.0,
        "entries": 37,
        "exits": 58
    },
    {
        "ending": 1526374800.0,
        "entries": 39,
        "exits": 5
    },
    {
        "ending": 1526389200.0,
        "entries": 1757,
        "exits": 75
    },
    {
        "ending": 1526403600.0,
        "entries": 800,
        "exits": 112
    },
    {
        "ending": 1526418000.0,
        "entries": 419,
        "exits": 136
    },
    {
        "ending": 1526432400.0,
        "entries": 191,
        "exits": 156
    },
    {
        "ending": 1526446800.0,
        "entries": 45,
        "exits": 48
    },
    {
        "ending": 1526461200.0,
        "entries": 40,
        "exits": 5
    },
    {
        "ending": 1526475600.0,
        "entries": 1677,
        "exits": 72
    },
    {
        "ending": 1526490000.0,
        "entries": 800,
        "exits": 104
    },
    {
        "ending": 1526504400.0,
        "entries": 435,
        "exits": 137
    },
    {
        "ending": 1526518800.0,
        "entries": 221,
        "exits": 147
    },
    {
        "ending": 1526533200.0,
        "entries": 45,
        "exits": 32
    },
    {
        "ending": 1526547600.0,
        "entries": 29,
        "exits": 7
    },
    {
        "ending": 1526562000.0,
        "entries": 1664,
        "exits": 64
    },
    {
        "ending": 1526576400.0,
        "entries": 759,
        "exits": 78
    },
    {
        "ending": 1526590800.0,
        "entries": 385,
        "exits": 131
    },
    {
        "ending": 1526605200.0,
        "entries": 242,
        "exits": 148
    },
    {
        "ending": 1526619600.0,
        "entries": 53,
        "exits": 56
    },
    {
        "ending": 1526634000.0,
        "entries": 31,
        "exits": 6
    },
    {
        "ending": 1526648400.0,
        "entries": 1585,
        "exits": 64
    },
    {
        "ending": 1526662800.0,
        "entries": 771,
        "exits": 85
    },
    {
        "ending": 1526677200.0,
        "entries": 402,
        "exits": 162
    },
    {
        "ending": 1526691600.0,
        "entries": 259,
        "exits": 143
    },
    {
        "ending": 1526706000.0,
        "entries": 52,
        "exits": 47
    },
    {
        "ending": 1526720400.0,
        "entries": 20,
        "exits": 6
    },
    {
        "ending": 1526734800.0,
        "entries": 505,
        "exits": 32
    },
    {
        "ending": 1526749200.0,
        "entries": 578,
        "exits": 115
    },
    {
        "ending": 1526763600.0,
        "entries": 249,
        "exits": 60
    },
    {
        "ending": 1526778000.0,
        "entries": 133,
        "exits": 94
    },
    {
        "ending": 1526792400.0,
        "entries": 46,
        "exits": 39
    },
    {
        "ending": 1526806800.0,
        "entries": 10,
        "exits": 7
    },
    {
        "ending": 1526821200.0,
        "entries": 281,
        "exits": 35
    },
    {
        "ending": 1526835600.0,
        "entries": 555,
        "exits": 120
    },
    {
        "ending": 1526850000.0,
        "entries": 271,
        "exits": 89
    },
    {
        "ending": 1526864400.0,
        "entries": 143,
        "exits": 97
    },
    {
        "ending": 1526878800.0,
        "entries": 22,
        "exits": 38
    },
    {
        "ending": 1526893200.0,
        "entries": 35,
        "exits": 7
    },
    {
        "ending": 1526907600.0,
        "entries": 1572,
        "exits": 63
    },
    {
        "ending": 1526922000.0,
        "entries": 760,
        "exits": 88
    },
    {
        "ending": 1526936400.0,
        "entries": 416,
        "exits": 144
    },
    {
        "ending": 1526950800.0,
        "entries": 205,
        "exits": 140
    },
    {
        "ending": 1526965200.0,
        "entries": 46,
        "exits": 40
    },
    {
        "ending": 1526979600.0,
        "entries": 44,
        "exits": 8
    },
    {
        "ending": 1526994000.0,
        "entries": 1715,
        "exits": 62
    },
    {
        "ending": 1527008400.0,
        "entries": 762,
        "exits": 93
    },
    {
        "ending": 1527022800.0,
        "entries": 397,
        "exits": 133
    },
    {
        "ending": 1527037200.0,
        "entries": 209,
        "exits": 128
    },
    {
        "ending": 1527051600.0,
        "entries": 47,
        "exits": 53
    },
    {
        "ending": 1527066000.0,
        "entries": 39,
        "exits": 9
    },
    {
        "ending": 1527080400.0,
        "entries": 1662,
        "exits": 66
    },
    {
        "ending": 1527094800.0,
        "entries": 791,
        "exits": 103
    },
    {
        "ending": 1527109200.0,
        "entries": 406,
        "exits": 162
    },
    {
        "ending": 1527123600.0,
        "entries": 251,
        "exits": 144
    },
    {
        "ending": 1527138000.0,
        "entries": 47,
        "exits": 50
    },
    {
        "ending": 1527152400.0,
        "entries": 43,
        "exits": 5
    },
    {
        "ending": 1527166800.0,
        "entries": 1651,
        "exits": 87
    },
    {
        "ending": 1527181200.0,
        "entries": 826,
        "exits": 92
    },
    {
        "ending": 1527195600.0,
        "entries": 425,
        "exits": 127
    },
    {
        "ending": 1527210000.0,
        "entries": 255,
        "exits": 157
    },
    {
        "ending": 1527224400.0,
        "entries": 44,
        "exits": 44
    },
    {
        "ending": 1527237900.0,
        "entries": 20,
        "exits": 4
    },
    {
        "ending": 1527238800.0,
        "entries": 17,
        "exits": 0
    },
    {
        "ending": 1527239700.0,
        "entries": 6,
        "exits": 0
    },
    {
        "ending": 1527253200.0,
        "entries": 1483,
        "exits": 72
    },
    {
        "ending": 1527267600.0,
        "entries": 785,
        "exits": 47
    },
    {
        "ending": 1527282000.0,
        "entries": 423,
        "exits": 158
    },
    {
        "ending": 1527296400.0,
        "entries": 232,
        "exits": 160
    },
    {
        "ending": 1527310800.0,
        "entries": 60,
        "exits": 57
    },
    {
        "ending": 1527325200.0,
        "entries": 21,
        "exits": 10
    },
    {
        "ending": 1527339600.0,
        "entries": 451,
        "exits": 38
    },
    {
        "ending": 1527354000.0,
        "entries": 577,
        "exits": 101
    },
    {
        "ending": 1527368400.0,
        "entries": 271,
        "exits": 87
    },
    {
        "ending": 1527382800.0,
        "entries": 139,
        "exits": 125
    },
    {
        "ending": 1527397200.0,
        "entries": 50,
        "exits": 59
    },
    {
        "ending": 1527411600.0,
        "entries": 14,
        "exits": 12
    },
    {
        "ending": 1527426000.0,
        "entries": 233,
        "exits": 31
    },
    {
        "ending": 1527440400.0,
        "entries": 424,
        "exits": 73
    },
    {
        "ending": 1527454800.0,
        "entries": 249,
        "exits": 88
    },
    {
        "ending": 1527469200.0,
        "entries": 127,
        "exits": 105
    },
    {
        "ending": 1527483600.0,
        "entries": 36,
        "exits": 39
    },
    {
        "ending": 1527498000.0,
        "entries": 15,
        "exits": 6
    },
    {
        "ending": 1527512400.0,
        "entries": 429,
        "exits": 33
    },
    {
        "ending": 1527526800.0,
        "entries": 641,
        "exits": 122
    },
    {
        "ending": 1527541200.0,
        "entries": 268,
        "exits": 111
    },
    {
        "ending": 1527555600.0,
        "entries": 144,
        "exits": 108
    },
    {
        "ending": 1527570000.0,
        "entries": 32,
        "exits": 53
    },
    {
        "ending": 1527584400.0,
        "entries": 36,
        "exits": 4
    },
    {
        "ending": 1527598800.0,
        "entries": 1655,
        "exits": 84
    },
    {
        "ending": 1527613200.0,
        "entries": 746,
        "exits": 109
    },
    {
        "ending": 1527627600.0,
        "entries": 379,
        "exits": 148
    },
    {
        "ending": 1527642000.0,
        "entries": 229,
        "exits": 133
    },
    {
        "ending": 1527656400.0,
        "entries": 43,
        "exits": 50
    },
    {
        "ending": 1527670800.0,
        "entries": 0,
        "exits": 0
    },
    {
        "ending": 1527685200.0,
        "entries": 1705,
        "exits": 73
    },
    {
        "ending": 1527699600.0,
        "entries": 749,
        "exits": 97
    },
    {
        "ending": 1527714000.0,
        "entries": 396,
        "exits": 148
    },
    {
        "ending": 1527728400.0,
        "entries": 223,
        "exits": 144
    },
    {
        "ending": 1527742800.0,
        "entries": 49,
        "exits": 46
    },
    {
        "ending": 1527757200.0,
        "entries": 0,
        "exits": 0
    },
    {
        "ending": 1527771600.0,
        "entries": 1693,
        "exits": 58
    },
    {
        "ending": 1527786000.0,
        "entries": 709,
        "exits": 89
    },
    {
        "ending": 1527800400.0,
        "entries": 410,
        "exits": 130
    },
    {
        "ending": 1527814800.0,
        "entries": 230,
        "exits": 117
    }
]